alex_mcp/__init__.py
alex_mcp/data_objects.py
alex_mcp/server.py
iflow_mcp_drabreu_alex_mcp-4.8.2.dist-info/licenses/LICENSE
iflow_mcp_drabreu_alex_mcp-4.8.2.dist-info/METADATA
iflow_mcp_drabreu_alex_mcp-4.8.2.dist-info/WHEEL
iflow_mcp_drabreu_alex_mcp-4.8.2.dist-info/entry_points.txt
iflow_mcp_drabreu_alex_mcp-4.8.2.dist-info/top_level.txt
iflow_mcp_drabreu_alex_mcp-4.8.2.dist-info/RECORD
