Metadata-Version: 2.4
Name: iflow-mcp_drabreu_alex-mcp
Version: 4.8.2
Summary: MCP server for OpenAlex academic research API
Home-page: https://github.com/drAbreu/alex-mcp
Author: OpenAlex MCP Team
Author-email: Jorge Abreu Vicente <jorge.abreu@embo.org>
License: MIT
Project-URL: Homepage, https://github.com/drAbreu/alex-mcp
Project-URL: Repository, https://github.com/drAbreu/alex-mcp
Project-URL: Issues, https://github.com/drAbreu/alex-mcp/issues
Classifier: Development Status :: 3 - Alpha
Classifier: Intended Audience :: Developers
Classifier: License :: OSI Approved :: MIT License
Classifier: Programming Language :: Python :: 3
Classifier: Programming Language :: Python :: 3.10
Classifier: Programming Language :: Python :: 3.11
Classifier: Programming Language :: Python :: 3.12
Requires-Python: >=3.10
License-File: LICENSE
Requires-Dist: fastmcp>=2.8.1
Requires-Dist: httpx>=0.28.1
Requires-Dist: pydantic>=2.7.2
Requires-Dist: rich>=13.9.4
Requires-Dist: pyalex==0.18
Requires-Dist: aiohttp>=3.8.0
Dynamic: author
Dynamic: home-page
Dynamic: license-file
Dynamic: requires-python
